setup.py
myzeromq.egg-info/PKG-INFO
myzeromq.egg-info/SOURCES.txt
myzeromq.egg-info/dependency_links.txt
myzeromq.egg-info/requires.txt
myzeromq.egg-info/top_level.txt
zeromq/__init__.py
zeromq/request.py
zeromq/response.py
zeromq/test_pb2.py