Metadata-Version: 1.1
Name: myzeromq
Version: 0.0.1
Summary: A request and response by using port
Home-page: https://github.com/arockiastanlya/myzeromq
Author: arockia stanly a
Author-email: stanly499@gmail.com
License: UNKNOWN
Platform: UNKNOWN
Classifier: Programming Language :: Python :: 3.5
